gyurcsany_szal.py
gyurcsany_szal-0.3.dist-info/LICENSE
gyurcsany_szal-0.3.dist-info/WHEEL
gyurcsany_szal-0.3.dist-info/METADATA
gyurcsany_szal-0.3.dist-info/RECORD
