Metadata-Version: 2.1
Name: gyurcsany_szal
Version: 0.3
Summary: A háttérben meghúzódó
Author-email: danthelion <danivgy@gmail.com>
Classifier: License :: OSI Approved :: MIT License
Project-URL: Home, https://github.com/danthelion/gyurcsany_szal
